data/__init__.py
data/info.txt
data/polylox_barcodelib.txt.zip
data/polylox_minrecs.txt.zip
data/polylox_path_matrix_ld_2017_reorder.txt.zip
data/polylox_path_matrix_uniform.txt.zip
polyloxpgen/__init__.py
polyloxpgen/merge.py
polyloxpgen/pgen.py
polyloxpgen-0.1.4.dist-info/LICENSE
polyloxpgen-0.1.4.dist-info/METADATA
polyloxpgen-0.1.4.dist-info/WHEEL
polyloxpgen-0.1.4.dist-info/top_level.txt
polyloxpgen-0.1.4.dist-info/RECORD
