Metadata-Version: 2.1
Name: polyloxpgen
Version: 0.1.4
Summary: Barcode purging and pgen (probability of generation) calculation for Polylox data.
Home-page: https://github.com/mauricelanghinrichs/polyloxpgen
Author: Maurice Langhinrichs
Author-email: m.langhinrichs@icloud.de
License: MIT
Platform: UNKNOWN
Classifier: Development Status :: 3 - Alpha
Classifier: License :: OSI Approved :: MIT License
Classifier: Programming Language :: Python
Classifier: Programming Language :: Python :: 3
Classifier: Programming Language :: Python :: 3.6
Classifier: Programming Language :: Python :: 3.7
Classifier: Programming Language :: Python :: 3.8
Classifier: Programming Language :: Python :: 3.9
Requires-Python: >=3.6
License-File: LICENSE
Requires-Dist: numpy (>=1.17.3)
Requires-Dist: pandas (>=1.1.0)
